pyvba/__init__.py
pyvba/browser.py
pyvba/export.py
pyvba/viewer.py
pyvba-0.6.0.dist-info/LICENSE
pyvba-0.6.0.dist-info/METADATA
pyvba-0.6.0.dist-info/WHEEL
pyvba-0.6.0.dist-info/top_level.txt
pyvba-0.6.0.dist-info/RECORD
