Metadata-Version: 2.1
Name: pyvba
Version: 0.6.0
Summary: Data mine and write scrips for VBA applications on Windows.
Home-page: https://github.com/TheEric960/pyvba
Author: Jack Wilson
License: UNKNOWN
Platform: UNKNOWN
Classifier: Development Status :: 3 - Alpha
Classifier: Environment :: Win32 (MS Windows)
Classifier: License :: OSI Approved :: MIT License
Classifier: Natural Language :: English
Classifier: Operating System :: Microsoft :: Windows
Classifier: Programming Language :: Python :: 3.7
Requires-Python: >=3.7
Requires-Dist: pywin32
